{
    "id":{
        "7":8,
        "37":38,
        "44":45
    },
    "firstName":{
        "7":"Bat",
        "37":"Dondog",
        "44":"Gerel"
    },
    "lastName":{
        "7":"Bayar",
        "37":"Saikhan",
        "44":"Saikhan"
    },
    "citizenId":{
        "7":"UB02",
        "37":"UB08",
        "44":"YK66"
    },
    "age":{
        "7":19,
        "37":20,
        "44":20
    },
    "yearsInCompany":{
        "7":6.0,
        "37":33.0,
        "44":19.0
    },
    "salary":{
        "7":2.4,
        "37":1.6870155463,
        "44":1.8721049677
    },
    "gender":{
        "7":"M",
        "37":"M",
        "44":"M"
    },
    "startDate":{
        "7":1437091200000,
        "37":"2020-01-10 00:00:00",
        "44":"2023-06-16 00:00:00"
    },
    "politicalView":{
        "7":"left",
        "37":"right",
        "44":"left"
    }
}